klatchat_utils/__init__.py
klatchat_utils/common.py
klatchat_utils/configuration.py
klatchat_utils/connection_utils.py
klatchat_utils/constants.py
klatchat_utils/exceptions.py
klatchat_utils/http_utils.py
klatchat_utils/logging_utils.py
klatchat_utils/template_utils.py
klatchat_utils/database_utils/__init__.py
klatchat_utils/database_utils/base_connector.py
klatchat_utils/database_utils/db_controller.py
klatchat_utils/database_utils/mongodb_connector.py
klatchat_utils/database_utils/mysql_connector.py
klatchat_utils/database_utils/mongo_utils/__init__.py
klatchat_utils/database_utils/mongo_utils/structures.py
klatchat_utils/database_utils/mongo_utils/user_utils.py
klatchat_utils/database_utils/mongo_utils/queries/__init__.py
klatchat_utils/database_utils/mongo_utils/queries/constants.py
klatchat_utils/database_utils/mongo_utils/queries/mongo_queries.py
klatchat_utils/database_utils/mongo_utils/queries/wrapper.py
klatchat_utils/database_utils/mongo_utils/queries/dao/__init__.py
klatchat_utils/database_utils/mongo_utils/queries/dao/abc.py
klatchat_utils/database_utils/mongo_utils/queries/dao/chats.py
klatchat_utils/database_utils/mongo_utils/queries/dao/configs.py
klatchat_utils/database_utils/mongo_utils/queries/dao/personas.py
klatchat_utils/database_utils/mongo_utils/queries/dao/prompts.py
klatchat_utils/database_utils/mongo_utils/queries/dao/shouts.py
klatchat_utils/database_utils/mongo_utils/queries/dao/users.py
tests/__init__.py
tests/test_common.py
tests/test_configuration.py
tests/test_connection_utils.py
tests/test_exceptions.py
tests/test_http_utils.py
tests/test_template_utils.py
tests/database_utils/__init__.py
tests/database_utils/mongo_utils/__init__.py
klatchat_utils-0.0.1a2.dist-info/LICENSE.md
klatchat_utils-0.0.1a2.dist-info/METADATA
klatchat_utils-0.0.1a2.dist-info/WHEEL
klatchat_utils-0.0.1a2.dist-info/top_level.txt
klatchat_utils-0.0.1a2.dist-info/RECORD
