Metadata-Version: 2.1
Name: klatchat-utils
Version: 0.0.1a2
Summary: Utilities for Klat
Home-page: https://github.com/neongeckocom/pyklatchat-utils
Author: Neongecko
Author-email: developers@neon.ai
License: BSD-3-Clause
Classifier: Programming Language :: Python :: 3
Classifier: Operating System :: OS Independent
Requires-Python: >=3.6
License-File: LICENSE.md
Requires-Dist: starlette
Requires-Dist: pymongo
Requires-Dist: jinja2
Requires-Dist: neon-utils~=1.0
Requires-Dist: ovos-utils~=0.0
Provides-Extra: sql
Requires-Dist: mysql; extra == "sql"
Requires-Dist: sshtunnel; extra == "sql"
Provides-Extra: test
Requires-Dist: pytest; extra == "test"
Requires-Dist: pytest-timeout; extra == "test"
Requires-Dist: pytest-cov; extra == "test"
